{
  "version": "1",
  "cognitoConfig": {
    "resourceNameTruncated": "greyhaf1204e2a",
    "userPoolName": "greyhammererpf1204e2a_userpool_f1204e2a",
    "autoVerifiedAttributes": [
      "phone_number"
    ],
    "mfaConfiguration": "OFF",
    "mfaTypes": [
      "SMS Text Message"
    ],
    "smsAuthenticationMessage": "Your authentication code is {####}",
    "smsVerificationMessage": "Your verification code is {####}",
    "emailVerificationSubject": "Your verification code",
    "emailVerificationMessage": "Your verification code is {####}",
    "defaultPasswordPolicy": false,
    "passwordPolicyMinLength": 8,
    "passwordPolicyCharacters": [],
    "requiredAttributes": [
      "email",
      "family_name",
      "given_name"
    ],
    "aliasAttributes": [],
    "userpoolClientGenerateSecret": false,
    "userpoolClientRefreshTokenValidity": 30,
    "userpoolClientWriteAttributes": [
      "email"
    ],
    "userpoolClientReadAttributes": [
      "email"
    ],
    "userpoolClientLambdaRole": "greyhaf1204e2a_userpoolclient_lambda_role",
    "userpoolClientSetAttributes": false,
    "sharedId": "f1204e2a",
    "resourceName": "greyhammererpf1204e2af1204e2a",
    "authSelections": "userPoolOnly",
    "useDefault": "manual",
    "usernameAttributes": [
      "email"
    ],
    "userPoolGroups": true,
    "adminQueries": false,
    "triggers": {},
    "hostedUI": false,
    "userPoolGroupList": [
      "admin",
      "operation",
      "accounting",
      "SE",
      "QS",
      "CE",
      "procurement"
    ],
    "serviceName": "Cognito",
    "usernameCaseSensitive": false,
    "useEnabledMfas": true
  }
}